odoo/addons/maintenance_plan_employee/README.rst
odoo/addons/maintenance_plan_employee/__init__.py
odoo/addons/maintenance_plan_employee/__manifest__.py
odoo/addons/maintenance_plan_employee/i18n/es.po
odoo/addons/maintenance_plan_employee/i18n/maintenance_plan_employee.pot
odoo/addons/maintenance_plan_employee/models/__init__.py
odoo/addons/maintenance_plan_employee/models/maintenance_equipment.py
odoo/addons/maintenance_plan_employee/models/maintenance_plan.py
odoo/addons/maintenance_plan_employee/readme/CONTRIBUTORS.rst
odoo/addons/maintenance_plan_employee/readme/DESCRIPTION.rst
odoo/addons/maintenance_plan_employee/static/description/icon.png
odoo/addons/maintenance_plan_employee/static/description/index.html
odoo/addons/maintenance_plan_employee/tests/__init__.py
odoo/addons/maintenance_plan_employee/tests/test_maintenance_plan_employee.py
odoo/addons/maintenance_plan_employee/views/maintenance_plan_views.xml
odoo/addons/maintenance_plan_employee/views/report_maintenance_request.xml
odoo13_addon_maintenance_plan_employee-13.0.1.1.0.dist-info/METADATA
odoo13_addon_maintenance_plan_employee-13.0.1.1.0.dist-info/WHEEL
odoo13_addon_maintenance_plan_employee-13.0.1.1.0.dist-info/top_level.txt
odoo13_addon_maintenance_plan_employee-13.0.1.1.0.dist-info/RECORD
