Metadata-Version: 2.1
Name: odoo13-addon-maintenance-plan-employee
Version: 13.0.1.1.0
Summary: Maintenance Plan Employee
Home-page: https://github.com/OCA/maintenance
Author: Tecnativa, Odoo Community Association (OCA)
Author-email: support@odoo-community.org
License: AGPL-3
Platform: UNKNOWN
Classifier: Programming Language :: Python
Classifier: Framework :: Odoo
Classifier: Framework :: Odoo :: 13.0
Classifier: License :: OSI Approved :: GNU Affero General Public License v3
Requires-Python: >=3.5
Requires-Dist: odoo13-addon-maintenance-plan
Requires-Dist: odoo13-addon-maintenance-request-employee
Requires-Dist: odoo (<13.1dev,>=13.0a)
